{
  "bar_id": "harmonic-f1bb7e1d19c4",
  "edo_interpretation": null,
  "global_order_index": 20,
  "instrument_id": "harmonic",
  "ji": {
    "ji_candidates": [
      {
        "cents_error": 6.88364345897337,
        "complexity_score": 1.584962500721156,
        "label": "3/1",
        "p": 3,
        "prime_limit": 5,
        "q": 1
      },
      {
        "cents_error": 6.88364345897337,
        "complexity_score": 1.584962500721156,
        "label": "3/1",
        "p": 3,
        "prime_limit": 7,
        "q": 1
      },
      {
        "cents_error": 6.88364345897337,
        "complexity_score": 1.584962500721156,
        "label": "3/1",
        "p": 3,
        "prime_limit": 11,
        "q": 1
      },
      {
        "cents_error": 6.88364345897337,
        "complexity_score": 1.584962500721156,
        "label": "3/1",
        "p": 3,
        "prime_limit": 13,
        "q": 1
      },
      {
        "cents_error": -14.622646137741594,
        "complexity_score": 11.076815597050832,
        "label": "80/27",
        "p": 80,
        "prime_limit": 5,
        "q": 27
      },
      {
        "cents_error": -6.9111231464219305,
        "complexity_score": 12.358101707440847,
        "label": "125/42",
        "p": 125,
        "prime_limit": 7,
        "q": 42
      },
      {
        "cents_error": -14.622646137741594,
        "complexity_score": 11.076815597050832,
        "label": "80/27",
        "p": 80,
        "prime_limit": 7,
        "q": 27
      },
      {
        "cents_error": -0.8278795323461501,
        "complexity_score": 14.036173612553485,
        "label": "224/75",
        "p": 224,
        "prime_limit": 7,
        "q": 75
      },
      {
        "cents_error": -10.6924876983083,
        "complexity_score": 11.659103963473662,
        "label": "98/33",
        "p": 98,
        "prime_limit": 11,
        "q": 33
      },
      {
        "cents_error": -6.9111231464219305,
        "complexity_score": 12.358101707440847,
        "label": "125/42",
        "p": 125,
        "prime_limit": 11,
        "q": 42
      }
    ],
    "ji_primary": {
      "cents_error": 6.88364345897337,
      "complexity_score": 1.584962500721156,
      "label": "3/1",
      "p": 3,
      "prime_limit": 5,
      "q": 1,
      "why": "closest weighted JI fit with 3/1 at 6.884 cents error, complexity 1.585, prime limit 5"
    }
  },
  "label_index_mod": null,
  "license": {
    "audio": "TBD",
    "metadata": "TBD",
    "spectrogram": "TBD"
  },
  "measurements": {
    "f0": {
      "f0_confidence": 0.4567539156016164,
      "f0_confidence_notes": "short audio; analysis window reduced; derived from natural filename order",
      "f0_corrections": null,
      "f0_distribution": {
        "iqr_hz": 1479.5454545454545,
        "max_hz": 2004.5454545454545,
        "median_hz": 525.0,
        "min_hz": 525.0,
        "n_frames": 78
      },
      "f0_hz": 525.0,
      "f0_method": "acf_median_tracker_v1",
      "f0_search": {
        "frame_size": 2028,
        "lmax": 1103,
        "lmin": 22,
        "max_hz": 2000.0,
        "median_lag": 84,
        "min_hz": 40.0
      },
      "f0_window": {
        "end_s": 1.1412471655328797,
        "start_s": 0.2
      },
      "harmonic_grid_fit": 0.16666666666666666
    },
    "partials": {
      "analysis_window": {
        "end_s": 1.1412471655328797,
        "start_s": 0.2
      },
      "peaks": [
        {
          "harmonic_index_guess": 1,
          "hz": 526.2176513671875,
          "peak_confidence": 1.0,
          "rel_amp_db": 0.0
        },
        {
          "harmonic_index_guess": null,
          "hz": 58.54339599609375,
          "peak_confidence": 1.0,
          "rel_amp_db": -17.455044747929342
        },
        {
          "harmonic_index_guess": null,
          "hz": 37.01019287109375,
          "peak_confidence": 0.688813957937049,
          "rel_amp_db": -18.430154015976058
        },
        {
          "harmonic_index_guess": null,
          "hz": 41.7205810546875,
          "peak_confidence": 0.5998240725949879,
          "rel_amp_db": -20.5625960292814
        },
        {
          "harmonic_index_guess": null,
          "hz": 119.7784423828125,
          "peak_confidence": 1.0,
          "rel_amp_db": -22.250608968161735
        },
        {
          "harmonic_index_guess": null,
          "hz": 69.98291015625,
          "peak_confidence": 0.7508604407480235,
          "rel_amp_db": -23.173188992903334
        },
        {
          "harmonic_index_guess": null,
          "hz": 105.64727783203125,
          "peak_confidence": 0.6543586560989414,
          "rel_amp_db": -26.053910223621248
        },
        {
          "harmonic_index_guess": 1,
          "hz": 509.39483642578125,
          "peak_confidence": 0.549224515315389,
          "rel_amp_db": -28.369886717663245
        },
        {
          "harmonic_index_guess": null,
          "hz": 90.84320068359375,
          "peak_confidence": 0.5190397340685787,
          "rel_amp_db": -28.38099263958221
        },
        {
          "harmonic_index_guess": null,
          "hz": 199.18212890625,
          "peak_confidence": 0.9635111180602304,
          "rel_amp_db": -30.244298498795985
        },
        {
          "harmonic_index_guess": null,
          "hz": 493.24493408203125,
          "peak_confidence": 0.9165240911468733,
          "rel_amp_db": -31.47225730740087
        },
        {
          "harmonic_index_guess": null,
          "hz": 541.021728515625,
          "peak_confidence": 0.667324060186837,
          "rel_amp_db": -31.55386089857718
        },
        {
          "harmonic_index_guess": null,
          "hz": 263.10882568359375,
          "peak_confidence": 1.0,
          "rel_amp_db": -31.658977120053798
        },
        {
          "harmonic_index_guess": null,
          "hz": 131.21795654296875,
          "peak_confidence": 0.5001331960644555,
          "rel_amp_db": -32.99202830640171
        },
        {
          "harmonic_index_guess": null,
          "hz": 109.68475341796875,
          "peak_confidence": 0.6379235697893314,
          "rel_amp_db": -33.828481532973036
        },
        {
          "harmonic_index_guess": null,
          "hz": 144.0032958984375,
          "peak_confidence": 0.5017013762646,
          "rel_amp_db": -33.925712087031805
        },
        {
          "harmonic_index_guess": null,
          "hz": 160.82611083984375,
          "peak_confidence": 0.5452912507153947,
          "rel_amp_db": -34.12782572668152
        },
        {
          "harmonic_index_guess": null,
          "hz": 177.64892578125,
          "peak_confidence": 0.5725647806652465,
          "rel_amp_db": -36.7553650244555
        },
        {
          "harmonic_index_guess": null,
          "hz": 403.74755859375,
          "peak_confidence": 0.7487155336443804,
          "rel_amp_db": -38.26382084527368
        },
        {
          "harmonic_index_guess": null,
          "hz": 328.38134765625,
          "peak_confidence": 0.968950196139352,
          "rel_amp_db": -38.598657539612326
        },
        {
          "harmonic_index_guess": null,
          "hz": 234.173583984375,
          "peak_confidence": 0.6164455380177636,
          "rel_amp_db": -38.69510215523935
        },
        {
          "harmonic_index_guess": null,
          "hz": 460.94512939453125,
          "peak_confidence": 0.6088491208138412,
          "rel_amp_db": -38.765150726148185
        },
        {
          "harmonic_index_guess": null,
          "hz": 378.84979248046875,
          "peak_confidence": 0.8326938745919698,
          "rel_amp_db": -39.122623136158595
        },
        {
          "harmonic_index_guess": null,
          "hz": 394.3267822265625,
          "peak_confidence": 0.7223591336688343,
          "rel_amp_db": -39.133876165435524
        },
        {
          "harmonic_index_guess": null,
          "hz": 297.4273681640625,
          "peak_confidence": 0.8711641026519847,
          "rel_amp_db": -39.48624917021777
        },
        {
          "harmonic_index_guess": null,
          "hz": 417.87872314453125,
          "peak_confidence": 0.7028327542822768,
          "rel_amp_db": -39.50127882131481
        },
        {
          "harmonic_index_guess": null,
          "hz": 576.01318359375,
          "peak_confidence": 0.7961138582573136,
          "rel_amp_db": -39.57483357030985
        },
        {
          "harmonic_index_guess": null,
          "hz": 304.82940673828125,
          "peak_confidence": 0.8534060025714653,
          "rel_amp_db": -39.7579884345127
        },
        {
          "harmonic_index_guess": null,
          "hz": 318.28765869140625,
          "peak_confidence": 0.5692579712143612,
          "rel_amp_db": -40.24724536670651
        },
        {
          "harmonic_index_guess": null,
          "hz": 568.6111450195312,
          "peak_confidence": 0.7575608821716986,
          "rel_amp_db": -40.28992054965422
        },
        {
          "harmonic_index_guess": null,
          "hz": 433.355712890625,
          "peak_confidence": 0.5754807124251187,
          "rel_amp_db": -40.46629154690808
        },
        {
          "harmonic_index_guess": null,
          "hz": 193.12591552734375,
          "peak_confidence": 0.5100313554172995,
          "rel_amp_db": -40.66938217461609
        },
        {
          "harmonic_index_guess": null,
          "hz": 247.6318359375,
          "peak_confidence": 0.5152257997952642,
          "rel_amp_db": -40.93028920743997
        },
        {
          "harmonic_index_guess": null,
          "hz": 368.08319091796875,
          "peak_confidence": 0.8470792074078186,
          "rel_amp_db": -40.935538853971835
        },
        {
          "harmonic_index_guess": null,
          "hz": 308.86688232421875,
          "peak_confidence": 0.5307574434960831,
          "rel_amp_db": -41.33802369277271
        },
        {
          "harmonic_index_guess": null,
          "hz": 598.2192993164062,
          "peak_confidence": 0.7650990094364001,
          "rel_amp_db": -41.392498482801614
        },
        {
          "harmonic_index_guess": null,
          "hz": 425.95367431640625,
          "peak_confidence": 0.5195680444597345,
          "rel_amp_db": -41.69546091344202
        },
        {
          "harmonic_index_guess": null,
          "hz": 401.055908203125,
          "peak_confidence": 0.5625672569616715,
          "rel_amp_db": -43.15026309916246
        },
        {
          "harmonic_index_guess": null,
          "hz": 1962.8860473632812,
          "peak_confidence": 1.0,
          "rel_amp_db": -44.557535430666846
        },
        {
          "harmonic_index_guess": null,
          "hz": 698.4832763671875,
          "peak_confidence": 0.7956515171860867,
          "rel_amp_db": -45.18130222154339
        },
        {
          "harmonic_index_guess": null,
          "hz": 632.537841796875,
          "peak_confidence": 0.6806466144220541,
          "rel_amp_db": -45.99678501166347
        },
        {
          "harmonic_index_guess": null,
          "hz": 680.987548828125,
          "peak_confidence": 0.7305302626562642,
          "rel_amp_db": -46.040491751925245
        },
        {
          "harmonic_index_guess": null,
          "hz": 773.8494873046875,
          "peak_confidence": 0.7902185267300906,
          "rel_amp_db": -46.45691727440108
        },
        {
          "harmonic_index_guess": null,
          "hz": 731.4559936523438,
          "peak_confidence": 0.6449292167714075,
          "rel_amp_db": -47.60463768377758
        },
        {
          "harmonic_index_guess": null,
          "hz": 713.9602661132812,
          "peak_confidence": 0.7147980617010722,
          "rel_amp_db": -48.39328990944097
        },
        {
          "harmonic_index_guess": null,
          "hz": 808.8409423828125,
          "peak_confidence": 0.9483387297277595,
          "rel_amp_db": -48.883385465553296
        },
        {
          "harmonic_index_guess": 2,
          "hz": 1029.5562744140625,
          "peak_confidence": 1.0,
          "rel_amp_db": -48.88364391667744
        },
        {
          "harmonic_index_guess": null,
          "hz": 848.5427856445312,
          "peak_confidence": 0.7245851518285773,
          "rel_amp_db": -48.946324052223886
        },
        {
          "harmonic_index_guess": null,
          "hz": 359.3353271484375,
          "peak_confidence": 0.5162404917774104,
          "rel_amp_db": -49.423979391213265
        },
        {
          "harmonic_index_guess": null,
          "hz": 924.5819091796875,
          "peak_confidence": 0.7488708392555489,
          "rel_amp_db": -49.73054040487075
        },
        {
          "harmonic_index_guess": null,
          "hz": 956.2088012695312,
          "peak_confidence": 0.7379399930671605,
          "rel_amp_db": -50.05230827935252
        },
        {
          "harmonic_index_guess": null,
          "hz": 789.9993896484375,
          "peak_confidence": 0.7061731758916674,
          "rel_amp_db": -50.342867665153825
        },
        {
          "harmonic_index_guess": null,
          "hz": 1983.0734252929688,
          "peak_confidence": 0.6273839312501251,
          "rel_amp_db": -50.370323625381786
        },
        {
          "harmonic_index_guess": null,
          "hz": 992.5460815429688,
          "peak_confidence": 0.668613672920895,
          "rel_amp_db": -50.71285372750313
        },
        {
          "harmonic_index_guess": null,
          "hz": 1918.4738159179688,
          "peak_confidence": 0.5792066659685075,
          "rel_amp_db": -50.73044471485908
        },
        {
          "harmonic_index_guess": null,
          "hz": 868.0572509765625,
          "peak_confidence": 0.6592998424638209,
          "rel_amp_db": -50.86122192571479
        },
        {
          "harmonic_index_guess": null,
          "hz": 1239.5050048828125,
          "peak_confidence": 1.0,
          "rel_amp_db": -51.1428756662541
        },
        {
          "harmonic_index_guess": null,
          "hz": 1189.0365600585938,
          "peak_confidence": 1.0,
          "rel_amp_db": -51.16305717965306
        },
        {
          "harmonic_index_guess": 2,
          "hz": 1040.3228759765625,
          "peak_confidence": 0.8026004001459701,
          "rel_amp_db": -51.165116281460335
        },
        {
          "harmonic_index_guess": null,
          "hz": 1174.9053955078125,
          "peak_confidence": 0.6391236723243016,
          "rel_amp_db": -51.27456358881883
        }
      ],
      "summary_peaks": [
        {
          "harmonic_index_guess": 1,
          "hz": 526.2176513671875,
          "peak_confidence": 1.0,
          "rel_amp_db": 0.0
        },
        {
          "harmonic_index_guess": null,
          "hz": 58.54339599609375,
          "peak_confidence": 1.0,
          "rel_amp_db": -17.455044747929342
        },
        {
          "harmonic_index_guess": null,
          "hz": 37.01019287109375,
          "peak_confidence": 0.688813957937049,
          "rel_amp_db": -18.430154015976058
        },
        {
          "harmonic_index_guess": null,
          "hz": 41.7205810546875,
          "peak_confidence": 0.5998240725949879,
          "rel_amp_db": -20.5625960292814
        },
        {
          "harmonic_index_guess": null,
          "hz": 119.7784423828125,
          "peak_confidence": 1.0,
          "rel_amp_db": -22.250608968161735
        },
        {
          "harmonic_index_guess": null,
          "hz": 69.98291015625,
          "peak_confidence": 0.7508604407480235,
          "rel_amp_db": -23.173188992903334
        },
        {
          "harmonic_index_guess": null,
          "hz": 105.64727783203125,
          "peak_confidence": 0.6543586560989414,
          "rel_amp_db": -26.053910223621248
        },
        {
          "harmonic_index_guess": 1,
          "hz": 509.39483642578125,
          "peak_confidence": 0.549224515315389,
          "rel_amp_db": -28.369886717663245
        },
        {
          "harmonic_index_guess": null,
          "hz": 90.84320068359375,
          "peak_confidence": 0.5190397340685787,
          "rel_amp_db": -28.38099263958221
        },
        {
          "harmonic_index_guess": null,
          "hz": 199.18212890625,
          "peak_confidence": 0.9635111180602304,
          "rel_amp_db": -30.244298498795985
        },
        {
          "harmonic_index_guess": null,
          "hz": 493.24493408203125,
          "peak_confidence": 0.9165240911468733,
          "rel_amp_db": -31.47225730740087
        },
        {
          "harmonic_index_guess": null,
          "hz": 541.021728515625,
          "peak_confidence": 0.667324060186837,
          "rel_amp_db": -31.55386089857718
        }
      ]
    },
    "sample_rate_hz": 44100
  },
  "media": {
    "audio_path": "audio/harmonic/harmonic-008.wav",
    "checksums": {
      "audio_sha256": "beb02725788e9a8960d974189a3c03b39e4aa05f5c069a96c63ce7eb9e5c0242"
    },
    "spectrogram_path": null,
    "youtube_url": null
  },
  "position_index": 8,
  "provenance": {
    "mallet": "",
    "measured_at": "",
    "measured_by": "",
    "method_version": "68bd384",
    "mic": "",
    "notes": "",
    "room": ""
  },
  "register": {
    "octave_abs": 1,
    "within_octave_ratio": 1.494047619047619
  },
  "revision_history": [
    {
      "by": "build_dataset.py",
      "change": "initial record creation",
      "date": "2026-02-09T21:52:34-08:00"
    }
  ],
  "source_filename": "harmonic-008.wav",
  "source_path": "audio/harmonic/harmonic-008.wav"
}
